eqcount/earthquake.py
eqcount-0.0.1.dist-info/LICENSE.txt
eqcount-0.0.1.dist-info/METADATA
eqcount-0.0.1.dist-info/WHEEL
eqcount-0.0.1.dist-info/top_level.txt
eqcount-0.0.1.dist-info/RECORD
